[
  {"id":"732555876","jobId":"1","jobTitle":"TA for Software Engineering (EBU6304)","taId":"u4","taName":"Alice Chen","taEmail":"ta1@bupt.edu.cn","status":"pending","appliedDate":"2026-03-31","coverLetter":""},
  {"id":"73255650","jobId":"1","jobTitle":"TA for Software Engineering (EBU6304)","taId":"u5","taName":"Bob Wang","taEmail":"ta2@bupt.edu.cn","status":"accepted","appliedDate":"2026-03-31","coverLetter":""},
  {"id":"7325596","jobId":"2","jobTitle":"TA for Data Structures (EBU5476)","taId":"u4","taName":"Alice Chen","taEmail":"ta1@bupt.edu.cn","status":"accepted","appliedDate":"2026-03-31","coverLetter":""}
]